setup.py
journal/__init__.py
journal_utils.egg-info/PKG-INFO
journal_utils.egg-info/SOURCES.txt
journal_utils.egg-info/dependency_links.txt
journal_utils.egg-info/not-zip-safe
journal_utils.egg-info/top_level.txt