Metadata-Version: 1.0
Name: journal-utils
Version: 0.1
Summary: Useful commands for handling and downloading peer-reviewed journal references.
Home-page: https://github.com/firstworldproblems/journal-utils
Author: faustus
Author-email: vince.cakic@gmail.com
License: MIT
Platform: UNKNOWN
